<?xml version="1.0" encoding="utf-8"?>
<ConstraintsData xmlns:xsd="http://www.w3.org/2001/XMLSchema" xmlns:xsi="http://www.w3.org/2001/XMLSchema-instance">
  <FlattenedNetName2ConstraintNetId />
  <CNets />
  <CNetClasses />
  <CDifferentialPairs />
  <CDifferentialPairClasses />
  <CPinPairs />
  <CxSigClasses />
  <CxNets />
  <CXNetClasses />
  <ConstraintClearancesMatrix>
    <CCMFromScopes>
      <CCMFromScope Id="aca2071f-4026-436d-8b1b-8ea063fa78ed">
        <ConstraintObject Id="00000000-0000-0000-0000-000000000000" />
        <CCMToScopes>
          <CCMToScope Id="f8d76fd4-0da0-4b87-94b3-0c9aaca1fcfb" SetId="00000000-0000-0000-0000-000000000000">
            <ConstraintObject Id="00000000-0000-0000-0000-000000000000" />
            <DefaultConstraintClearancesMatrixConstraint Id="00000000-0000-0000-0000-000000000000" Kind="0" Name="" Description="" Scope1="" Scope2="" Attributes="" LayerType="0" LayerId="0" />
            <CCMConstraints />
          </CCMToScope>
        </CCMToScopes>
      </CCMFromScope>
    </CCMFromScopes>
  </ConstraintClearancesMatrix>
  <ConstraintSameNetClearancesMatrix>
    <CCMFromScopes />
  </ConstraintSameNetClearancesMatrix>
  <CSets />
  <CClearancesMatrixSets />
</ConstraintsData>